bashcalc/__init__.py
bashcalc/bashcalc.py
bashcalc-1.0.dist-info/LICENSE
bashcalc-1.0.dist-info/METADATA
bashcalc-1.0.dist-info/WHEEL
bashcalc-1.0.dist-info/entry_points.txt
bashcalc-1.0.dist-info/top_level.txt
bashcalc-1.0.dist-info/RECORD
