Metadata-Version: 2.1
Name: bashcalc
Version: 1.0
Summary: Instant calculating from the terminal into the terminal
Home-page: https://github.com/Anselmoo/bashcalc
Author: Anselm Hahn
Author-email: Anselm.Hahn@gmail.com
Maintainer: Anselm Hahn
Maintainer-email: Anselm.Hahn@gmail.com
License: MIT
Keywords: console,terminal,calculator,data-science,shell,bash
Platform: UNKNOWN
Classifier: Development Status :: 5 - Production/Stable
Classifier: Environment :: Console
Classifier: Intended Audience :: Developers
Classifier: Intended Audience :: Information Technology
Classifier: Intended Audience :: End Users/Desktop
Classifier: Intended Audience :: Science/Research
Classifier: License :: OSI Approved :: MIT License
Classifier: Operating System :: MacOS
Classifier: Operating System :: Unix
Classifier: Programming Language :: Python :: 3
Classifier: Programming Language :: Python :: 3.6
Classifier: Programming Language :: Python :: 3.7
Classifier: Programming Language :: Python :: 3.8
Classifier: Topic :: Software Development :: Widget Sets
Classifier: Topic :: System :: Shells
Classifier: Topic :: Terminals
Classifier: Topic :: Utilities
Provides-Extra: testing
Requires-Dist: pipenv ; extra == 'testing'
